nonebot_plugin_mcqq/__init__.py
nonebot_plugin_mcqq/data_source.py
nonebot_plugin_mcqq_test-0.0.2.dist-info/LICENSE
nonebot_plugin_mcqq_test-0.0.2.dist-info/METADATA
nonebot_plugin_mcqq_test-0.0.2.dist-info/WHEEL
nonebot_plugin_mcqq_test-0.0.2.dist-info/top_level.txt
nonebot_plugin_mcqq_test-0.0.2.dist-info/RECORD
