Metadata-Version: 2.1
Name: nonebot-plugin-mcqq-test
Version: 0.0.2
Summary: 基于NoneBot的QQ群聊与Minecraft Server消息互通插件
Home-page: https://github.com/17TheWord/nonebot-plugin-mcqq
Author: 17TheWord
Author-email: 17theword@gmail.com
Classifier: Programming Language :: Python :: 3.10
Classifier: License :: OSI Approved :: GNU Affero General Public License v3
Classifier: Operating System :: OS Independent
License-File: LICENSE
Requires-Dist: nonebot2 (>=2.0.0b4)
Requires-Dist: nonebot-adapter-onebot (>=2.1.1)
Requires-Dist: nonebot-plugin-guild-patch (>=0.2.0)
Requires-Dist: websockets (>=10.3)
